onfire/__init__.py
onfire/data.py
onfire/embedders.py
onfire/fields.py
onfire/pipeline.py
onfire/transformers.py
onfire/transformers_bak.py
onfire/utils.py
onfire/colab/__init__.py
onfire/colab/runners.py
pytorch_onfire-0.1.3.dist-info/LICENSE
pytorch_onfire-0.1.3.dist-info/METADATA
pytorch_onfire-0.1.3.dist-info/WHEEL
pytorch_onfire-0.1.3.dist-info/top_level.txt
pytorch_onfire-0.1.3.dist-info/RECORD
