Metadata-Version: 2.1
Name: pytorch-onfire
Version: 0.1.3
Summary: PyTorch meets Sklearn Pipelines.
Home-page: https://github.com/joshfp/pytorch-onfire
Author: Jose Fernandez Portal, Rafael Carrascosa
Author-email: jose.fp@gmail.com
License: MIT
Platform: UNKNOWN
Classifier: Intended Audience :: Developers
Classifier: Topic :: Software Development
Classifier: Development Status :: 4 - Beta
Classifier: Programming Language :: Python
Classifier: Programming Language :: Python :: 3
Classifier: Programming Language :: Python :: 3.6
Classifier: Programming Language :: Python :: 3.7
Classifier: Programming Language :: Python :: 3.8
Requires-Python: >=3.6
Requires-Dist: torch
Requires-Dist: scikit-learn
Requires-Dist: Unidecode
Requires-Dist: lmdb
Requires-Dist: msgpack
Requires-Dist: fastprogress
Requires-Dist: matplotlib
